[
  {
    "id": "wizards",
    "name": "Wizards of Moonhill",
    "coverAudio": {
      "front": {
        "src": "",
        "startDelayMs": 800,
        "custom": false
      },
      "back": {
        "src": "",
        "startDelayMs": 800,
        "custom": false
      }
    },
    "pages": [
      {
        "pageNumber": 1,
        "audio": {
          "src": "",
          "startDelayMs": 1000,
          "custom": false
        },
        "hasDialogChoice": false,
        "dialog": null
      },
      {
        "pageNumber": 2,
        "audio": {
          "src": "",
          "startDelayMs": 1000,
          "custom": false
        },
        "hasDialogChoice": true,
        "dialog": {
          "question": "Which spell should the wizard try first?",
          "options": [
            "Light spell",
            "Shield spell",
            "Wind spell"
          ]
        }
      },
      {
        "pageNumber": 3,
        "audio": {
          "src": "",
          "startDelayMs": 1200,
          "custom": false
        },
        "hasDialogChoice": false,
        "dialog": null
      },
      {
        "pageNumber": 4,
        "audio": {
          "src": "",
          "startDelayMs": 1000,
          "custom": false
        },
        "hasDialogChoice": true,
        "dialog": {
          "question": "Where should the wizard travel next?",
          "options": [
            "Crystal cave",
            "Forest tower"
          ]
        }
      }
    ]
  },
  {
    "id": "dragons",
    "storyId": "rainbow_sea_of_starfall",
    "storyTitle": "The Rainbow Sea of Starfall",
    "narrator": "Captain Coral",
    "name": "The Rainbow Sea of Starfall",
    "coverAudio": {
      "front": {
        "src": "custom_front.mp3",
        "startDelayMs": 0,
        "custom": true
      },
      "back": {
        "src": "",
        "startDelayMs": 0,
        "custom": false
      }
    },
    "pages": [
      {
        "pageNumber": 1,
        "image": "page1.jpg",
        "audio": {
          "src": "page1.mp3",
          "startDelayMs": 0,
          "custom": false
        },
        "hasDialogChoice": false,
        "dialog": null
      },
      {
        "pageNumber": 2,
        "image": "page2.jpg",
        "audio": {
          "src": "page2.mp3",
          "startDelayMs": 0,
          "custom": false
        },
        "hasDialogChoice": false,
        "dialog": null
      },
      {
        "pageNumber": 3,
        "choiceChapter": 1,
        "image": "page3.jpg",
        "audio": [
		  {
            "src": "custom_name.mp3",
            "startDelayMs": 0,
            "custom": true
          },
          {
            "src": "page3_question_intro.mp3",
            "startDelayMs": 0,
            "custom": false
          },
          {
            "src": "page3_choices.mp3",
            "startDelayMs": 0,
            "custom": false
          }
        ],
        "hasDialogChoice": true,
        "dialog": {
          "question": "What shall we do?",
          "options": [
            {
              "label": "Walk slowly onto the bridge and speak gently to Lumi",
              "tags": ["approach_behavior", "calm_bravery", "emotional_attunement", "gentle_support"]
            },
            {
              "label": "Ask Captain Coral to come help rescue Lumi together",
              "tags": ["help_seeking", "trust_in_adult", "collaborative_coping", "social_problem_solving"]
            },
            {
              "label": "Wait behind a crystal pillar until the storm gets quieter",
              "tags": ["avoidance", "threat_sensitivity", "behavioral_inhibition", "cautious_temperament"]
            }
          ]
        },
        "choiceOutcomes": {
          "Walk slowly onto the bridge and speak gently to Lumi": {
            "image": "page3_a.jpg",
            "audio": {
              "src": "page3_a.mp3",
              "startDelayMs": 0,
              "custom": false
            }
          },
          "Ask Captain Coral to come help rescue Lumi together": {
            "image": "page3_b.jpg",
            "audio": {
              "src": "page3_b.mp3",
              "startDelayMs": 0,
              "custom": false
            }
          },
          "Wait behind a crystal pillar until the storm gets quieter": {
            "image": "page3_c.jpg",
            "audio": {
              "src": "page3_c.mp3",
              "startDelayMs": 0,
              "custom": false
            }
          }
        }
      },
      {
        "pageNumber": 4,
        "image": "page4.jpg",
        "audio": {
          "src": "page4.mp3",
          "startDelayMs": 0,
          "custom": false
        },
        "hasDialogChoice": false,
        "dialog": null
      },
      {
        "pageNumber": 5,
        "image": "page5.jpg",
        "audio": {
          "src": "page5.mp3",
          "startDelayMs": 0,
          "custom": false
        },
        "hasDialogChoice": false,
        "dialog": null
      },
      {
        "pageNumber": 6,
        "choiceChapter": 2,
        "image": "page6.jpg",
        "audio": {
          "src": "page6.mp3",
          "startDelayMs": 0,
          "custom": false
        },
        "hasDialogChoice": true,
        "dialog": {
          "question": "Which shell needs you first?",
          "options": [
            {
              "label": "Open the trembling shell first and say, \"This one feels scared.\"",
              "tags": ["emotion_recognition_fear", "emotional_awareness", "emotional_attunement", "sensitivity_to_distress"]
            },
            {
              "label": "Open the blue tear-shell first and say, \"This one feels lonely or sad.\"",
              "tags": ["emotion_recognition_sadness", "empathy", "emotional_awareness", "sensitivity_to_sadness"]
            },
            {
              "label": "Ignore the shells and look directly for the shard",
              "tags": ["emotion_avoidance", "task_over_emotion", "low_affective_engagement", "goal_directed_focus"]
            }
          ]
        },
        "choiceOutcomes": {
          "Open the trembling shell first and say, \"This one feels scared.\"": {
            "image": "page6_a.jpg",
            "audio": {
              "src": "page6_a.mp3",
              "startDelayMs": 0,
              "custom": false
            }
          },
          "Open the blue tear-shell first and say, \"This one feels lonely or sad.\"": {
            "image": "page6_b.jpg",
            "audio": {
              "src": "page6_b.mp3",
              "startDelayMs": 0,
              "custom": false
            }
          },
          "Ignore the shells and look directly for the shard": {
            "image": "page6_c.jpg",
            "audio": {
              "src": "page6_c.mp3",
              "startDelayMs": 0,
              "custom": false
            }
          }
        }
      },
      {
        "pageNumber": 7,
        "image": "page7.jpg",
        "audio": {
          "src": "page7.mp3",
          "startDelayMs": 0,
          "custom": false
        },
        "hasDialogChoice": false,
        "dialog": null
      },
      {
        "pageNumber": 8,
        "image": "page8.jpg",
        "audio": {
          "src": "page8.mp3",
          "startDelayMs": 0,
          "custom": false
        },
        "hasDialogChoice": false,
        "dialog": null
      },
      {
        "pageNumber": 9,
        "choiceChapter": 3,
        "image": "page9.jpg",
        "audio": {
          "src": "page9.mp3",
          "startDelayMs": 0,
          "custom": false
        },
        "hasDialogChoice": true,
        "dialog": {
          "question": "What kind of magic shall we make here?",
          "options": [
            {
              "label": "Invite Finn to sit with you and say, \"Everyone gets a place.\"",
              "tags": ["prosocial_behavior", "peer_inclusion", "fairness_orientation", "assertive_kindness", "defending_behavior"]
            },
            {
              "label": "Tell Captain Coral or another grown pirate that something unfair is happening",
              "tags": ["help_seeking_social", "trust_in_adult", "fairness_orientation", "safe_conflict_response"]
            },
            {
              "label": "Stay quiet so the loud pirates do not get upset",
              "tags": ["social_avoidance", "conflict_avoidance", "bystander_passivity", "fear_of_retaliation", "peer_distress_sensitivity"]
            }
          ]
        },
        "choiceOutcomes": {
          "Invite Finn to sit with you and say, \"Everyone gets a place.\"": {
            "image": "page9_a.jpg",
            "audio": {
              "src": "page9_a.mp3",
              "startDelayMs": 0,
              "custom": false
            }
          },
          "Tell Captain Coral or another grown pirate that something unfair is happening": {
            "image": "page9_b.jpg",
            "audio": {
              "src": "page9_b.mp3",
              "startDelayMs": 0,
              "custom": false
            }
          },
          "Stay quiet so the loud pirates do not get upset": {
            "image": "page9_c.jpg",
            "audio": {
              "src": "page9_c.mp3",
              "startDelayMs": 0,
              "custom": false
            }
          }
        }
      },
      {
        "pageNumber": 10,
        "image": "page10.jpg",
        "audio": {
          "src": "page10.mp3",
          "startDelayMs": 0,
          "custom": false
        },
        "hasDialogChoice": false,
        "dialog": null
      },
      {
        "pageNumber": 11,
        "image": "page11.jpg",
        "audio": {
          "src": "page11.mp3",
          "startDelayMs": 0,
          "custom": false
        },
        "hasDialogChoice": false,
        "dialog": null
      },
      {
        "pageNumber": 12,
        "choiceChapter": 4,
        "image": "page12.jpg",
        "audio": {
          "src": "page12.mp3",
          "startDelayMs": 0,
          "custom": false
        },
        "hasDialogChoice": true,
        "dialog": {
          "question": "What do we do with heavy feelings?",
          "options": [
            {
              "label": "Tell Marina, \"Some feelings are too heavy to hold alone.\"",
              "tags": ["safe_disclosure", "help_seeking", "trust_in_supportive_other", "emotional_openness"]
            },
            {
              "label": "Tell Lumi and ask him to stay beside you while you think",
              "tags": ["co_regulation", "proximity_seeking", "relational_coping", "partial_disclosure"]
            },
            {
              "label": "Close the chest and keep moving without opening it",
              "tags": ["secrecy", "emotional_suppression", "avoidance", "discomfort_with_disclosure"]
            }
          ]
        },
        "choiceOutcomes": {
          "Tell Marina, \"Some feelings are too heavy to hold alone.\"": {
            "image": "page12_a.jpg",
            "audio": {
              "src": "page12_a.mp3",
              "startDelayMs": 0,
              "custom": false
            }
          },
          "Tell Lumi and ask him to stay beside you while you think": {
            "image": "page12_b.jpg",
            "audio": {
              "src": "page12_b.mp3",
              "startDelayMs": 0,
              "custom": false
            }
          },
          "Close the chest and keep moving without opening it": {
            "image": "page12_c.jpg",
            "audio": {
              "src": "page12_c.mp3",
              "startDelayMs": 0,
              "custom": false
            }
          }
        }
      },
      {
        "pageNumber": 13,
        "image": "page13.jpg",
        "audio": {
          "src": "page13.mp3",
          "startDelayMs": 0,
          "custom": false
        },
        "hasDialogChoice": false,
        "dialog": null
      },
      {
        "pageNumber": 14,
        "image": "page14.jpg",
        "audio": {
          "src": "page14.mp3",
          "startDelayMs": 0,
          "custom": false
        },
        "hasDialogChoice": false,
        "dialog": null
      },
      {
        "pageNumber": 15,
        "choiceChapter": 5,
        "image": "page15.jpg",
        "audio": {
          "src": "page15.mp3",
          "startDelayMs": 0,
          "custom": false
        },
        "hasDialogChoice": true,
        "dialog": {
          "question": "How is the Heart-Star restored?",
          "options": [
            {
              "label": "Place your hand on the Heart-Star and say how you feel out loud",
              "tags": ["emotion_expression", "emotional_awareness", "self_regulation", "emotional_honesty"]
            },
            {
              "label": "Ask all your friends to help restore it together",
              "tags": ["collaborative_coping", "help_seeking", "trust_in_others", "social_resilience"]
            },
            {
              "label": "Try to fix it alone without saying anything",
              "tags": ["independent_coping", "low_help_seeking", "emotional_withholding", "self_reliance"]
            }
          ]
        },
        "choiceOutcomes": {
          "Place your hand on the Heart-Star and say how you feel out loud": {
            "image": "page15_a.jpg",
            "audio": {
              "src": "page15_a.mp3",
              "startDelayMs": 0,
              "custom": false
            }
          },
          "Ask all your friends to help restore it together": {
            "image": "page15_b.jpg",
            "audio": {
              "src": "page15_b.mp3",
              "startDelayMs": 0,
              "custom": false
            }
          },
          "Try to fix it alone without saying anything": {
            "image": "page15_c.jpg",
            "audio": {
              "src": "page15_c.mp3",
              "startDelayMs": 0,
              "custom": false
            }
          }
        }
      },
      {
        "pageNumber": 16,
        "image": "page16.jpg",
        "audio": {
          "src": "page16.mp3",
          "startDelayMs": 0,
          "custom": false
        },
        "hasDialogChoice": false,
        "dialog": null
      }
    ]
  },
  {
    "id": "princess",
    "name": "Princess of Starlight",
    "coverAudio": {
      "front": {
        "src": "",
        "startDelayMs": 800,
        "custom": false
      },
      "back": {
        "src": "",
        "startDelayMs": 800,
        "custom": false
      }
    },
    "pages": [
      {
        "pageNumber": 1,
        "audio": {
          "src": "",
          "startDelayMs": 1100,
          "custom": false
        },
        "hasDialogChoice": false,
        "dialog": null
      },
      {
        "pageNumber": 2,
        "audio": {
          "src": "",
          "startDelayMs": 1000,
          "custom": false
        },
        "hasDialogChoice": true,
        "dialog": {
          "question": "Which path should the princess follow?",
          "options": [
            "Moon bridge",
            "Garden gate"
          ]
        }
      },
      {
        "pageNumber": 3,
        "audio": {
          "src": "",
          "startDelayMs": 1000,
          "custom": false
        },
        "hasDialogChoice": false,
        "dialog": null
      },
      {
        "pageNumber": 4,
        "audio": {
          "src": "",
          "startDelayMs": 1000,
          "custom": false
        },
        "hasDialogChoice": true,
        "dialog": {
          "question": "Who should join the royal quest?",
          "options": [
            "Knight",
            "Inventor",
            "Poet"
          ]
        }
      }
    ]
  },
  {
    "id": "mermaids",
    "name": "Mermaids of Coral Bay",
    "coverAudio": {
      "front": {
        "src": "",
        "startDelayMs": 800,
        "custom": false
      },
      "back": {
        "src": "",
        "startDelayMs": 800,
        "custom": false
      }
    },
    "pages": [
      {
        "pageNumber": 1,
        "audio": {
          "src": "",
          "startDelayMs": 1000,
          "custom": false
        },
        "hasDialogChoice": false,
        "dialog": null
      },
      {
        "pageNumber": 2,
        "audio": {
          "src": "",
          "startDelayMs": 1000,
          "custom": false
        },
        "hasDialogChoice": true,
        "dialog": {
          "question": "What should the mermaid collect first?",
          "options": [
            "Pearl",
            "Sea map"
          ]
        }
      },
      {
        "pageNumber": 3,
        "audio": {
          "src": "",
          "startDelayMs": 950,
          "custom": false
        },
        "hasDialogChoice": false,
        "dialog": null
      },
      {
        "pageNumber": 4,
        "audio": {
          "src": "",
          "startDelayMs": 1000,
          "custom": false
        },
        "hasDialogChoice": false,
        "dialog": null
      }
    ]
  }
]
